{
  "index_patterns": [
    "idx_interview"
  ],
  "mappings": {
    "properties": {
      "candidate": {
        "properties": {
          "full_name": {
            "type": "text",
            "analyzer": "whitespace",
            "fields": {
              "keyword": {
                "type": "keyword",
                "normalizer": "lowercase",
                "ignore_above": 256
              }
            }
          },
          "id": {
            "type": "long"
          }
        }
      },
      "created_at": {
        "type": "date",
        "fields": {
          "keyword": {
            "type": "keyword",
            "ignore_above": 50
          }
        }
      },
      "date_time": {
        "type": "date",
        "fields": {
          "keyword": {
            "type": "keyword",
            "ignore_above": 50
          }
        }
      },
      "description": {
        "type": "text",
        "fields": {
          "keyword": {
            "type": "keyword",
            "ignore_above": 256
          }
        }
      },
      "has_result": {
        "type": "boolean"
      },
      "id": {
        "type": "long"
      },
      "is_deleted": {
        "type": "boolean"
      },
      "reminder_count": {
        "type": "long"
      },
      "status": {
        "type": "text",
        "fields": {
          "keyword": {
            "type": "keyword",
            "normalizer": "lowercase",
            "ignore_above": 256
          }
        }
      },
      "title": {
        "type": "text",
        "fields": {
          "keyword": {
            "type": "keyword",
            "ignore_above": 256
          }
        }
      },
      "type": {
        "type": "text",
        "fields": {
          "keyword": {
            "type": "keyword",
            "ignore_above": 256
          }
        }
      },
      "updated_at": {
        "type": "date"
      }
    }
  },
  "order": 4
}